hasiihelper/Dimensions.py
hasiihelper/Position.py
hasiihelper/ResourceManager.py
hasiihelper/SemanticVersion.py
hasiihelper/Singleton.py
hasiihelper/UnitTestBase.py
hasiihelper/__init__.py
hasiihelper/py.typed
hasiihelper-0.2.1.dist-info/LICENSE
hasiihelper-0.2.1.dist-info/METADATA
hasiihelper-0.2.1.dist-info/WHEEL
hasiihelper-0.2.1.dist-info/top_level.txt
hasiihelper-0.2.1.dist-info/RECORD
