Metadata-Version: 2.1
Name: hasiihelper
Version: 0.2.1
Summary: Humberto`s Helper Classes
Home-page: https://github.com/hasii2011/hasiihelper
Author: Humberto A. Sanchez II
Author-email: Humberto.A.Sanchez.II@gmail.com
Maintainer: Humberto A. Sanchez II
Maintainer-email: humberto.a.sanchez.ii@gmail.com
License-File: LICENSE
Requires-Dist: Deprecated (~=1.2.14)
